setup.py
distributions_PR/Binomialdistribution.py
distributions_PR/Gaussiandistribution.py
distributions_PR/Generaldistribution.py
distributions_PR/__init__.py
distributions_PR.egg-info/PKG-INFO
distributions_PR.egg-info/SOURCES.txt
distributions_PR.egg-info/dependency_links.txt
distributions_PR.egg-info/not-zip-safe
distributions_PR.egg-info/top_level.txt