Metadata-Version: 1.0
Name: distributions-PR
Version: 0.1
Summary: Gaussian distributions
Home-page: UNKNOWN
Author: ['Pouya']
Author-email: UNKNOWN
License: UNKNOWN
Platform: UNKNOWN
